PyMCT/Log.py
PyMCT/MCT.py
PyMCT/__init__.py
PyMCT-1.2.2.dist-info/LICENSE
PyMCT-1.2.2.dist-info/METADATA
PyMCT-1.2.2.dist-info/WHEEL
PyMCT-1.2.2.dist-info/top_level.txt
PyMCT-1.2.2.dist-info/RECORD
