Metadata-Version: 2.1
Name: PyMCT
Version: 1.2.2
Summary: A simple implement for MCTS algorithm.
Author-email: Yifei Ren <ryf0510@live.com>
Project-URL: Homepage, https://github.com/ulfaric/PyMCT
Project-URL: Bug Tracker, https://github.com/ulfaric/PyMCT/issues
Classifier: Programming Language :: Python :: 3
Classifier: License :: OSI Approved :: GNU General Public License v3 (GPLv3)
Classifier: Operating System :: OS Independent
Requires-Python: >=3.7
License-File: LICENSE
Requires-Dist: anytree
Requires-Dist: unique-names-generator
